.coveragerc
.editorconfig
.gitattributes
CHANGES.rst
CONTRIBUTORS.rst
Gruntfile.js
MANIFEST.in
README.rst
base.cfg
bobtemplate.cfg
buildout.cfg
constraints.txt
constraints_plone51.txt
constraints_plone52.txt
package-lock.json
package.json
requirements.txt
setup.cfg
setup.py
test_plone51.cfg
test_plone52.cfg
versions.cfg
docs/LICENSE.GPL
docs/LICENSE.rst
docs/index.rst
src/redturtle/__init__.py
src/redturtle.tiles.management.egg-info/PKG-INFO
src/redturtle.tiles.management.egg-info/SOURCES.txt
src/redturtle.tiles.management.egg-info/dependency_links.txt
src/redturtle.tiles.management.egg-info/entry_points.txt
src/redturtle.tiles.management.egg-info/namespace_packages.txt
src/redturtle.tiles.management.egg-info/not-zip-safe
src/redturtle.tiles.management.egg-info/requires.txt
src/redturtle.tiles.management.egg-info/top_level.txt
src/redturtle/tiles/__init__.py
src/redturtle/tiles/management/__init__.py
src/redturtle/tiles/management/configure.zcml
src/redturtle/tiles/management/event_handler.py
src/redturtle/tiles/management/interfaces.py
src/redturtle/tiles/management/setuphandlers.py
src/redturtle/tiles/management/testing.py
src/redturtle/tiles/management/upgrades.zcml
src/redturtle/tiles/management/vocabularies.py
src/redturtle/tiles/management/browser/__init__.py
src/redturtle/tiles/management/browser/add.py
src/redturtle/tiles/management/browser/configure.zcml
src/redturtle/tiles/management/browser/controlpanel.py
src/redturtle/tiles/management/browser/delete.py
src/redturtle/tiles/management/browser/edit.py
src/redturtle/tiles/management/browser/tiles_management.py
src/redturtle/tiles/management/browser/tiles_view.py
src/redturtle/tiles/management/browser/traversal.py
src/redturtle/tiles/management/browser/vocabulary.py
src/redturtle/tiles/management/browser/overrides/.gitkeep
src/redturtle/tiles/management/browser/overrides/plone.app.tiles.browser.add.pt
src/redturtle/tiles/management/browser/overrides/plone.app.tiles.browser.tileformlayout.pt
src/redturtle/tiles/management/browser/static/.gitkeep
src/redturtle/tiles/management/browser/static/bundle.js
src/redturtle/tiles/management/browser/static/integration.css
src/redturtle/tiles/management/browser/static/integration.css.map
src/redturtle/tiles/management/browser/static/integration.js
src/redturtle/tiles/management/browser/static/loader.svg
src/redturtle/tiles/management/browser/static/polyfill.min.js
